mcp_foxxy_bridge/__init__.py
mcp_foxxy_bridge/__main__.py
mcp_foxxy_bridge/py.typed
mcp_foxxy_bridge/cli/__init__.py
mcp_foxxy_bridge/cli/api_client.py
mcp_foxxy_bridge/cli/daemon_manager.py
mcp_foxxy_bridge/cli/formatters.py
mcp_foxxy_bridge/cli/main.py
mcp_foxxy_bridge/cli/commands/__init__.py
mcp_foxxy_bridge/cli/commands/config.py
mcp_foxxy_bridge/cli/commands/logs.py
mcp_foxxy_bridge/cli/commands/mcp_handlers.py
mcp_foxxy_bridge/cli/commands/oauth.py
mcp_foxxy_bridge/cli/commands/security_handlers.py
mcp_foxxy_bridge/cli/commands/server.py
mcp_foxxy_bridge/cli/commands/tool.py
mcp_foxxy_bridge/clients/__init__.py
mcp_foxxy_bridge/clients/sse_client.py
mcp_foxxy_bridge/clients/sse_client_wrapper.py
mcp_foxxy_bridge/clients/stdio_client_wrapper.py
mcp_foxxy_bridge/clients/streamablehttp_client.py
mcp_foxxy_bridge/config/__init__.py
mcp_foxxy_bridge/config/auth_config.py
mcp_foxxy_bridge/config/config_loader.py
mcp_foxxy_bridge/config/server_config.py
mcp_foxxy_bridge/config/validation.py
mcp_foxxy_bridge/oauth/__init__.py
mcp_foxxy_bridge/oauth/config.py
mcp_foxxy_bridge/oauth/coordination.py
mcp_foxxy_bridge/oauth/events.py
mcp_foxxy_bridge/oauth/http_security.py
mcp_foxxy_bridge/oauth/oauth_client_provider.py
mcp_foxxy_bridge/oauth/oauth_flow.py
mcp_foxxy_bridge/oauth/types.py
mcp_foxxy_bridge/oauth/utils.py
mcp_foxxy_bridge/security/__init__.py
mcp_foxxy_bridge/security/classifier.py
mcp_foxxy_bridge/security/config.py
mcp_foxxy_bridge/security/controller.py
mcp_foxxy_bridge/security/patterns.py
mcp_foxxy_bridge/security/policy.py
mcp_foxxy_bridge/server/__init__.py
mcp_foxxy_bridge/server/bridge_server.py
mcp_foxxy_bridge/server/bridge_server_config.py
mcp_foxxy_bridge/server/mcp_server.py
mcp_foxxy_bridge/server/proxy_server.py
mcp_foxxy_bridge/server/server_manager.py
mcp_foxxy_bridge/utils/__init__.py
mcp_foxxy_bridge/utils/bridge_config.py
mcp_foxxy_bridge/utils/bridge_home.py
mcp_foxxy_bridge/utils/config_migration.py
mcp_foxxy_bridge-1.7.1.dist-info/METADATA
mcp_foxxy_bridge-1.7.1.dist-info/WHEEL
mcp_foxxy_bridge-1.7.1.dist-info/entry_points.txt
mcp_foxxy_bridge-1.7.1.dist-info/licenses/LICENSE
mcp_foxxy_bridge-1.7.1.dist-info/RECORD
