Metadata-Version: 2.4
Name: mcp-foxxy-bridge
Version: 1.7.1
Summary: A MCP Forward Proxy Bridge designed to be a one-to-many bridge allowing you to use a single MCP server to communicate with many MCP servers transparently.
Project-URL: Homepage, https://github.com/billyjbryant/mcp-foxxy-bridge
Project-URL: Source, https://github.com/billyjbryant/mcp-foxxy-bridge
Project-URL: Documentation, https://github.com/billyjbryant/mcp-foxxy-bridge
Project-URL: Changelog, https://github.com/billyjbryant/mcp-foxxy-bridge/releases
Author-email: Billy Bryant <billy@billyjbryant.com>
License: GNU AFFERO GENERAL PUBLIC LICENSE
License-File: LICENSE
Classifier: Development Status :: 4 - Beta
Classifier: Environment :: Console
Classifier: Intended Audience :: Developers
Classifier: Intended Audience :: Information Technology
Classifier: Intended Audience :: System Administrators
Classifier: License :: OSI Approved :: GNU Affero General Public License v3 or later (AGPLv3+)
Classifier: Operating System :: MacOS
Classifier: Operating System :: POSIX :: Linux
Classifier: Operating System :: Unix
Classifier: Programming Language :: Python
Classifier: Programming Language :: Python :: 3
Classifier: Programming Language :: Python :: 3 :: Only
Classifier: Programming Language :: Python :: 3.11
Classifier: Programming Language :: Python :: 3.12
Classifier: Programming Language :: Python :: 3.13
Classifier: Topic :: Software Development :: Libraries :: Python Modules
Classifier: Topic :: Utilities
Classifier: Typing :: Typed
Requires-Python: >=3.11
Requires-Dist: aiohttp>=3.12.15
Requires-Dist: click>=8.1.0
Requires-Dist: cryptography>=3.4.8
Requires-Dist: events>=0.5
Requires-Dist: httpx[http2]>=0.28.0
Requires-Dist: jsonschema>=4.0.0
Requires-Dist: keyring>=23.0.0
Requires-Dist: mcp<2.0.0,>=1.8.0
Requires-Dist: psutil>=5.9.0
Requires-Dist: pyyaml>=6.0.0
Requires-Dist: rich-click>=1.7.0
Requires-Dist: rich>=13.0.0
Requires-Dist: uvicorn>=0.34.0
Requires-Dist: watchdog>=3.0.0
